pdfize/__init__.py
pdfize/__main__.py
pdfize/info.py
pdfize/py.typed
pdfize/new_process/__init__.py
pdfize/new_process/init.py
pdfize/new_process/lock.py
pdfize/processor/__init__.py
pdfize/processor/base.py
pdfize/processor/image_processor.py
pdfize/processor/pdf_processor.py
pdfize/progress_bar/__init__.py
pdfize/progress_bar/base.py
pdfize/progress_bar/cli.py
pdfize/progress_bar/enums.py
pdfize/util/__init__.py
pdfize/util/path_util.py
pdfize/util/pdf_util.py
pdfize-0.3.5.dist-info/METADATA
pdfize-0.3.5.dist-info/WHEEL
pdfize-0.3.5.dist-info/entry_points.txt
pdfize-0.3.5.dist-info/licenses/LICENSE
pdfize-0.3.5.dist-info/RECORD
