Metadata-Version: 2.4
Name: pdfize
Version: 0.3.5
Summary: Just a simple command-line tool for converting PDF files into images, with support for multiprocessing to enhance performance.
Project-URL: Repository, https://github.com/rogeliokg/pdfize
License: AGPL-3.0
License-File: LICENSE
Classifier: Environment :: Console
Classifier: License :: OSI Approved :: GNU Affero General Public License v3
Classifier: Programming Language :: Python :: 3
Classifier: Programming Language :: Python :: 3.11
Classifier: Topic :: Utilities
Requires-Python: >=3.11
Requires-Dist: click-help-colors>=0.9.4
Requires-Dist: click>=8.1.8
Requires-Dist: pillow>=11.1.0
Requires-Dist: pymupdf==1.24.9
Requires-Dist: tqdm>=4.67.1
